lurklite/__init__.py
lurklite/__main__.py
lurklite/core.py
lurklite/static_cmds.py
lurklite/tempcmds.py
lurklite-0.4.27.dist-info/LICENSE.md
lurklite-0.4.27.dist-info/METADATA
lurklite-0.4.27.dist-info/WHEEL
lurklite-0.4.27.dist-info/entry_points.txt
lurklite-0.4.27.dist-info/top_level.txt
lurklite-0.4.27.dist-info/RECORD
