Metadata-Version: 2.1
Name: lurklite
Version: 0.4.27
Summary: A miniirc-based IRC bot.
Home-page: https://github.com/luk3yx/lurklite
Author: luk3yx
License: AGPLv3
Classifier: Development Status :: 5 - Production/Stable
Classifier: License :: OSI Approved :: GNU Affero General Public License v3
Classifier: Operating System :: OS Independent
Classifier: Programming Language :: Python :: 3
Classifier: Programming Language :: Python :: 3.4
Classifier: Programming Language :: Python :: 3.5
Classifier: Programming Language :: Python :: 3.6
Classifier: Programming Language :: Python :: 3.7
Classifier: Programming Language :: Python :: 3.8
Requires-Python: >=3.6
License-File: LICENSE.md
Requires-Dist: miniirc (>=1.8.0)
Requires-Dist: msgpack
